pandas2hdf/__init__.py
pandas2hdf/core.py
pandas2hdf-1.0.0.dist-info/licenses/LICENSE
pandas2hdf-1.0.0.dist-info/METADATA
pandas2hdf-1.0.0.dist-info/WHEEL
pandas2hdf-1.0.0.dist-info/top_level.txt
pandas2hdf-1.0.0.dist-info/RECORD
