Metadata-Version: 2.4
Name: pandas2hdf
Version: 1.0.0
Summary: Robust round-trip persistence between pandas and HDF5 with SWMR support
Requires-Python: >=3.10
License-File: LICENSE
Requires-Dist: h5py>=3.7.0
Requires-Dist: pandas>=1.5.0
Requires-Dist: numpy>=1.21.0
Dynamic: license-file
